upowpy/__init__.py
upowpy/push.py
upowpy/upow_transactions/__init__.py
upowpy/upow_transactions/coinbase_transaction.py
upowpy/upow_transactions/constants.py
upowpy/upow_transactions/helpers.py
upowpy/upow_transactions/transaction.py
upowpy/upow_transactions/transaction_input.py
upowpy/upow_transactions/transaction_output.py
upowpy/utils/__init__.py
upowpy/utils/repository.py
upowpy/utils/utils.py
upowpy-1.0.8.dist-info/METADATA
upowpy-1.0.8.dist-info/WHEEL
upowpy-1.0.8.dist-info/top_level.txt
upowpy-1.0.8.dist-info/RECORD
